pylogs/__init__.py
pylogs/main.py
pylogs_DIGITAL_MARKEMATICS-1.0.3.dist-info/LICENSE
pylogs_DIGITAL_MARKEMATICS-1.0.3.dist-info/METADATA
pylogs_DIGITAL_MARKEMATICS-1.0.3.dist-info/WHEEL
pylogs_DIGITAL_MARKEMATICS-1.0.3.dist-info/top_level.txt
pylogs_DIGITAL_MARKEMATICS-1.0.3.dist-info/RECORD
